LICENCE
README.rst
setup.cfg
setup.py
mycore/DBController.py
mycore/DateFormat.py
mycore/__init__.py
mycore/test.py
mycore.egg-info/PKG-INFO
mycore.egg-info/SOURCES.txt
mycore.egg-info/dependency_links.txt
mycore.egg-info/top_level.txt