Metadata-Version: 2.1
Name: mycore
Version: 0.0.3
Summary: scn core lib by python
Home-page: https://github.com/shenarder
Author: Huan Zhou
Author-email: shenarder@163.com
Classifier: Programming Language :: Python :: 3
Classifier: License :: OSI Approved :: MIT License
Classifier: Operating System :: OS Independent
Requires-Python: >=3.6
License-File: LICENCE
